django_obfuscate-0.1.2.dist-info/DESCRIPTION.rst
django_obfuscate-0.1.2.dist-info/METADATA
django_obfuscate-0.1.2.dist-info/RECORD
django_obfuscate-0.1.2.dist-info/WHEEL
django_obfuscate-0.1.2.dist-info/metadata.json
django_obfuscate-0.1.2.dist-info/top_level.txt
obfuscator/__init__.py
obfuscator/apps.py
obfuscator/conf.py
obfuscator/utils.py
obfuscator/management/__init__.py
obfuscator/management/commands/__init__.py
obfuscator/management/commands/obfuscate.py
obfuscator/tests/__init__.py
obfuscator/tests/test_commands.py
obfuscator/tests/test_conf.py
obfuscator/tests/test_utils.py
